aiida_wannier90/__init__.py
aiida_wannier90/orbitals.py
aiida_wannier90/utils.py
aiida_wannier90/calculations/__init__.py
aiida_wannier90/calculations/postw90.py
aiida_wannier90/calculations/wannier90.py
aiida_wannier90/io/__init__.py
aiida_wannier90/io/_group_list.py
aiida_wannier90/io/_write_win.py
aiida_wannier90/parsers/__init__.py
aiida_wannier90/parsers/postw90.py
aiida_wannier90/parsers/wannier90.py
aiida_wannier90/workflows/__init__.py
aiida_wannier90/workflows/minimal.py
aiida_wannier90-2.2.0.dist-info/entry_points.txt
aiida_wannier90-2.2.0.dist-info/LICENSE.txt
aiida_wannier90-2.2.0.dist-info/WHEEL
aiida_wannier90-2.2.0.dist-info/METADATA
aiida_wannier90-2.2.0.dist-info/RECORD
