Metadata-Version: 2.1
Name: aiida-wannier90
Version: 2.2.0
Summary: AiiDA Plugin for the Wannier90 code
Keywords: aiida,plugin,wannier90
Author: Junfeng Qiao, Dominik Gresch, Antimo Marrazzo, Daniel Marchand, Giovanni Pizzi, Norma Rivano, The AiiDA team
Requires-Python: >=3.9
Classifier: Development Status :: 5 - Production/Stable
Classifier: Framework :: AiiDA
Classifier: Environment :: Plugins
Classifier: License :: OSI Approved :: MIT License
Classifier: Operating System :: POSIX :: Linux
Classifier: Operating System :: MacOS :: MacOS X
Classifier: Programming Language :: Python
Classifier: Programming Language :: Python :: 3.9
Classifier: Programming Language :: Python :: 3.10
Classifier: Programming Language :: Python :: 3.11
Classifier: Programming Language :: Python :: 3.12
Classifier: Natural Language :: English
Classifier: Topic :: Scientific/Engineering :: Physics
Classifier: Intended Audience :: Science/Research
Requires-Dist: aiida-core>=2.0,<3
Requires-Dist: sphinx ; extra == "docs"
Requires-Dist: sphinx-rtd-theme ; extra == "docs"
Requires-Dist: sphinxcontrib-details-directive ; extra == "docs"
Requires-Dist: pre-commit ; extra == "pre-commit"
Requires-Dist: pylint>=3 ; extra == "pre-commit"
Requires-Dist: yapf>=0.28 ; extra == "pre-commit"
Requires-Dist: prospector>=1.3.1 ; extra == "pre-commit"
Requires-Dist: ruamel.yaml ; extra == "pre-commit"
Requires-Dist: pytest ; extra == "tests"
Requires-Dist: pytest-cov ; extra == "tests"
Requires-Dist: pytest-regressions ; extra == "tests"
Requires-Dist: pytest-datadir ; extra == "tests"
Requires-Dist: pgtest ; extra == "tests"
Project-URL: Documentation, https://aiida-wannier90.readthedocs.io
Project-URL: Source, https://github.com/aiidateam/aiida-wannier90
Provides-Extra: docs
Provides-Extra: pre-commit
Provides-Extra: tests
